jsonquery/__init__.py
jsonquery/jsonquery.py
jsonquery/test.py
arkho_jsonquery-0.0.5.dist-info/LICENSE
arkho_jsonquery-0.0.5.dist-info/METADATA
arkho_jsonquery-0.0.5.dist-info/WHEEL
arkho_jsonquery-0.0.5.dist-info/top_level.txt
arkho_jsonquery-0.0.5.dist-info/RECORD
