Metadata-Version: 2.1
Name: arkho-jsonquery
Version: 0.0.5
Summary: Prototype of query path over JSON files
Home-page: https://github.com/arkhotech/json_query.git
Author: Marcelo Silva
Author-email: msilva@arkhotech.com
License: UNKNOWN
Platform: UNKNOWN
Classifier: Development Status :: 2 - Pre-Alpha
Classifier: Operating System :: OS Independent
Classifier: License :: OSI Approved :: GNU General Public License (GPL)
Classifier: Intended Audience :: Developers
Classifier: Natural Language :: Spanish
Classifier: Programming Language :: Python :: 3.7
Classifier: Topic :: Software Development :: Libraries :: Python Modules
Requires-Python: >=3.6
